osn_var_tools/__init__.py
osn_var_tools/format_tools.py
osn_var_tools/python_instances_tools.py
osn_var_tools/var_utilities.py
osn_var_tools/math/__init__.py
osn_var_tools/math/basic_vars.py
osn_var_tools/math/graph_2D.py
osn_var_tools/math/vars.py
osn_var_tools-1.0.0.dist-info/METADATA
osn_var_tools-1.0.0.dist-info/WHEEL
osn_var_tools-1.0.0.dist-info/top_level.txt
osn_var_tools-1.0.0.dist-info/RECORD
