Metadata-Version: 2.2
Name: osn-var-tools
Version: 1.0.0
Summary: osn-var-tools is a Python library providing a versatile toolkit for variable manipulation, formatting, introspection, and data handling, simplifying common tasks and enhancing code clarity.
Author: oddshellnick
Author-email: oddshellnick.programming@gmail.com
Requires-Dist: setuptools>=75.1.0
Requires-Dist: numpy>=2.1.3
Requires-Dist: pandas>=2.2.3
Requires-Dist: parameterized>=0.9.0
Requires-Dist: python-dateutil>=2.9.0.post0
Dynamic: author
Dynamic: author-email
Dynamic: description
Dynamic: description-content-type
Dynamic: requires-dist
Dynamic: summary
